urilibplus/__init__.py
urilibplus/characters.py
urilibplus/tools.py
urilibplus/typings.py
urilibplus/uri.py
urilibplus/uri_path.py
urilibplus/uri_query.py
urilibplus-1.0.0.0.dist-info/LICENCE
urilibplus-1.0.0.0.dist-info/METADATA
urilibplus-1.0.0.0.dist-info/WHEEL
urilibplus-1.0.0.0.dist-info/top_level.txt
urilibplus-1.0.0.0.dist-info/zip-safe
urilibplus-1.0.0.0.dist-info/RECORD
