Metadata-Version: 2.1
Name: urilibplus
Version: 1.0.0.0
Summary: A Python module providing advanced tools for URI manipulation and validation. Simplifies handling and parsing of URIs, with a focus on robustness and ease of use.
Author-email: Markus Hammer <107761433+MarkusHammer@users.noreply.github.com>
Project-URL: Homepage, https://github.com/MarkusHammer/urilibplus-python
Project-URL: Documentation, https://MarkusHammer.gthub.io/urilibplus-python
Project-URL: Github, https://github.com/MarkusHammer/urilibplus-python
Project-URL: Issues, https://github.com/MarkusHammer/urilibplus-python/issues
Project-URL: Pull Requests, https://github.com/MarkusHammer/urilibplus-python/pulls
Project-URL: Git, https://github.com/MarkusHammer/urilibplus-python.git
Keywords: uri,url,http,https,path manipulation,uri parsing,url validation,web development,networking,internet
Classifier: License :: OSI Approved :: Mozilla Public License 2.0 (MPL 2.0)
Classifier: Development Status :: 5 - Production/Stable
Classifier: Intended Audience :: Developers
Classifier: Typing :: Typed
Classifier: Natural Language :: English
Classifier: Topic :: Internet :: WWW/HTTP
Classifier: Topic :: Software Development
Classifier: Topic :: Utilities
Classifier: Programming Language :: Python
Classifier: Programming Language :: Python :: 3
Classifier: Programming Language :: Python :: 3.7
Classifier: Programming Language :: Python :: 3.8
Classifier: Programming Language :: Python :: 3.9
Classifier: Programming Language :: Python :: 3.10
Classifier: Programming Language :: Python :: 3.11
Requires-Python: >=3.7
License-File: LICENCE
Requires-Dist: typing-extensions <=3.10
Provides-Extra: dev
Requires-Dist: setuptools >=64.0.0 ; extra == 'dev'
Requires-Dist: pip-tools ; extra == 'dev'
Requires-Dist: validate-pyproject[all] ; extra == 'dev'
Requires-Dist: build ; extra == 'dev'
Requires-Dist: twine ; extra == 'dev'
Requires-Dist: coverage ; extra == 'dev'
Requires-Dist: pdoc3 ; extra == 'dev'
Requires-Dist: pyright ; extra == 'dev'
Requires-Dist: pylint ; extra == 'dev'
